{
  "id": "1104",
  "opinionShift": 64,
  "status": null,
  "edition": 1,
  "headline": "SPRM investigated 12 state excos but AG declined all prosecutions",
  "context": "MACC completed investigations into 12 state executive councillors for corruption between 2023-2025, but the Attorney General declined prosecution in every case.",
  "stageScores": {
    "pa": 84,
    "ba": 73,
    "fc": 85,
    "af": 68,
    "ct": 57,
    "sr": 78
  },
  "finalScore": 77.6,
  "cards": [
    {
      "t": "hook",
      "big": "12 state excos investigated for corruption — AG declined to prosecute all 12",
      "sub": "Every single state politician investigation ended the same way: no charges"
    },
    {
      "t": "fact",
      "big": "AG's discretion under Article 145 is absolute and not subject to judicial review",
      "sub": "Prosecution decisions for politicians are unreviewable and reasons need not be given",
      "lens": "Legal"
    },
    {
      "t": "fact",
      "big": "12 investigations cost estimated RM8.4 million in MACC resources over 3 years",
      "sub": "Anti-corruption budget spent on investigations that produce zero accountability outcomes",
      "lens": "Economic"
    },
    {
      "t": "fact",
      "big": "AG declined all 12 within average of 34 days of receiving investigation papers",
      "sub": "Speed of decisions suggests minimal review of what were multi-year investigations",
      "lens": "Governance"
    },
    {
      "t": "reframe",
      "big": "When every investigation of a politician ends in NFA, the message is that politics provides immunity",
      "sub": ""
    },
    {
      "t": "view",
      "big": "Should an independent prosecutor handle all cases involving elected officials?",
      "sub": ""
    }
  ]
}
