{
  "id": "1249",
  "opinionShift": 68,
  "status": "updated",
  "edition": 1,
  "headline": "Mandatory sentencing affects 23 offences under Malaysian law",
  "context": "Legal reform advocates highlighted that 23 offences in Malaysian statutes still carry mandatory minimum sentences, limiting judicial discretion.",
  "stageScores": {
    "pa": 79,
    "ba": 66,
    "fc": 83,
    "af": 63,
    "ct": 50,
    "sr": 75
  },
  "finalScore": 74,
  "cards": [
    {
      "t": "hook",
      "big": "23 Malaysian offences still impose mandatory minimum sentences on judges",
      "sub": "Judicial discretion restricted despite 2023 death penalty reforms"
    },
    {
      "t": "fact",
      "big": "Firearms Act 1960 Section 8 mandates death or life imprisonment",
      "sub": "No room for judges to consider mitigating circumstances in sentencing",
      "lens": "Legal"
    },
    {
      "t": "fact",
      "big": "Bar Council called for review of all 23 mandatory sentences in 2024",
      "sub": "Proportionality in punishment is a recognised human rights principle",
      "lens": "Rights"
    },
    {
      "t": "fact",
      "big": "Over 4,600 prisoners serving mandatory terms as of December 2024",
      "sub": "Many are first-time offenders who received no sentencing mitigation",
      "lens": "Social"
    },
    {
      "t": "reframe",
      "big": "Does mandatory sentencing deliver justice or merely uniformity?",
      "sub": ""
    },
    {
      "t": "view",
      "big": "Law Reform Commission recommended reducing mandatory sentences to 15 offences in 2022",
      "sub": ""
    }
  ]
}
