{
  "id": "1366",
  "opinionShift": 62,
  "status": null,
  "edition": 1,
  "headline": "University Autonomy Index Places Malaysia at 34 of 50 Countries",
  "context": "The European University Association's 2025 global autonomy index ranked Malaysia low on institutional self-governance.",
  "stageScores": {
    "pa": 78,
    "ba": 77,
    "fc": 80,
    "af": 72,
    "ct": 59,
    "sr": 79
  },
  "finalScore": 75.9,
  "cards": [
    {
      "t": "hook",
      "big": "Malaysia ranked 34th out of 50 countries in university autonomy index 2025",
      "sub": "Organizational staffing financial and academic autonomy all scored below median"
    },
    {
      "t": "fact",
      "big": "Vice-Chancellors of all 20 public universities are appointed by the Minister of Education",
      "sub": "No public university has an independent governing board selection process",
      "lens": "Governance"
    },
    {
      "t": "fact",
      "big": "Public universities cannot set tuition fees or create new programs without MOE approval",
      "sub": "Approval process averages 18 months delaying response to industry needs",
      "lens": "Governance"
    },
    {
      "t": "fact",
      "big": "QS World Rankings show only 5 Malaysian universities in top 200 in 2026",
      "sub": "Autonomy constraints are linked to slower institutional improvement rates",
      "lens": "Critical"
    },
    {
      "t": "reframe",
      "big": "Universities controlled by politics produce research that serves politics not knowledge",
      "sub": ""
    },
    {
      "t": "view",
      "big": "Should public universities have independent boards free from ministerial appointment",
      "sub": ""
    }
  ]
}
