{
  "id": "1519",
  "opinionShift": 53,
  "status": null,
  "edition": 1,
  "headline": "Hospital Bed Occupancy Rate Exceeds 90% at 28 Government Hospitals",
  "context": "Overcrowding at public hospitals persists with 28 facilities operating above safe occupancy levels throughout 2025.",
  "stageScores": {
    "pa": 88,
    "ba": 65,
    "fc": 88,
    "af": 61,
    "ct": 46,
    "sr": 72
  },
  "finalScore": 85.8,
  "cards": [
    {
      "t": "hook",
      "big": "28 government hospitals operated above 90% bed occupancy throughout 2025",
      "sub": "International safety standard recommends maximum 85% occupancy for infection control"
    },
    {
      "t": "fact",
      "big": "Patient corridor admissions reported at 12 hospitals due to bed unavailability",
      "sub": "Corridor patients receive reduced monitoring and higher infection exposure",
      "lens": "Health"
    },
    {
      "t": "fact",
      "big": "Malaysia has 1.9 hospital beds per 1,000 population versus OECD average of 4.3",
      "sub": "Bed shortfall of approximately 45,000 beds drives chronic overcrowding",
      "lens": "Governance"
    },
    {
      "t": "fact",
      "big": "Vietnam expanded hospital capacity 35% through public-private partnership bed-sharing agreements",
      "sub": "Contracted private hospital beds absorbed overflow during peak demand periods",
      "lens": "Critical"
    },
    {
      "t": "reframe",
      "big": "Hospitals operating at unsafe occupancy levels put every patient at risk not just those on corridors",
      "sub": ""
    },
    {
      "t": "view",
      "big": "Should Malaysia build 20 new hospitals by 2030 to bring bed ratio to international standards",
      "sub": ""
    }
  ]
}
