{"id":"1401","published":true,"opinionShift":92,"status":"new","edition":1,"headline":"Sijil Kemahiran Malaysia Holders Earn 40% Less Than Degree Holders","context":"Skills certificate holders face persistent wage discrimination despite equivalent competency in technical fields.","stageScores":{"pa":84,"ba":69,"fc":84,"af":65,"ct":51,"sr":75},"finalScore":73.9,"cards":[{"t":"hook","big":"SKM Level 4 holders earn average RM2,100 versus RM3,500 for degree holders in same fields","sub":"Wage gap persists even when job functions are identical between qualifications"},{"t":"fact","big":"Malaysian Qualifications Framework places SKM and degrees at equivalent levels since 2007","sub":"Formal equivalence has not translated to employer recognition or pay parity","lens":"Economic"},{"t":"fact","big":"74% of employers in MIHRM 2025 survey require degrees for jobs performable by SKM holders","sub":"Credentialism rather than competency drives hiring practices","lens":"Social"},{"t":"fact","big":"Switzerland's vocational diploma holders earn 92% of university graduate salaries on average","sub":"Strong industry-certification linkage ensures skills-based pay not credential-based","lens":"Critical"},{"t":"reframe","big":"Devaluing skills certificates while promoting TVET sends contradictory signals to young people","sub":""},{"t":"view","big":"Should government mandate equal pay for equivalent MQF-level qualifications in public sector","sub":""}]}