{"id":"1471","published":true,"opinionShift":93,"status":"new","edition":1,"headline":"Opioid Substitution Therapy Waitlist Grows to 8,500 Patients","context":"Methadone and buprenorphine treatment programs cannot accommodate growing demand from opioid-dependent patients.","stageScores":{"pa":86,"ba":69,"fc":85,"af":64,"ct":51,"sr":76},"finalScore":81.2,"cards":[{"t":"hook","big":"8,500 patients on waitlist for opioid substitution therapy as of December 2025","sub":"Only 52,000 of estimated 170,000 opioid users receive any form of treatment"},{"t":"fact","big":"Average wait time for methadone program entry is 4.5 months in Klang Valley","sub":"Patients waiting for treatment face overdose risk 6 times higher than those in treatment","lens":"Health"},{"t":"fact","big":"Government methadone clinics operate only during office hours excluding working patients","sub":"Rigid scheduling forces patients to choose between treatment and employment","lens":"Governance"},{"t":"fact","big":"France expanded OST through community pharmacies reaching 180,000 patients since 2018","sub":"Pharmacy-based distribution dramatically increased treatment accessibility and retention","lens":"Critical"},{"t":"reframe","big":"Making people wait months for addiction treatment is sentencing them to continued suffering","sub":""},{"t":"analogy","big":"Like making diabetics queue 8 months for insulin — the treatment exists, the patients are identified, but the bottleneck is between them","sub":"Addiction is a medical condition with effective treatment; the waitlist converts a treatable condition into preventable suffering"},{"t":"view","big":"Should opioid substitution therapy be available through community pharmacies not just clinics","sub":""}]}