{"id":"1766","opinionShift":74,"status":null,"edition":1,"headline":"Water Infrastructure Losses Hit RM7.2 Billion Every Year","context":"Non-revenue water losses across Malaysia reached 36.4% translating to RM7.2 billion in lost treated water annually.","stageScores":{"pa":85,"ba":83,"fc":83,"af":68,"ct":45,"sr":75},"finalScore":73.9,"cards":[{"t":"hook","big":"Malaysia loses RM7.2 billion in treated water annually from 36.4% NRW","sub":"Pipe leaks and theft account for over one-third of all treated water"},{"t":"fact","big":"Selangor NRW at 31% means 580 million litres leak from pipes daily","sub":"Air Selangor replaced only 280km of 32,000km pipe network in 2025","lens":"Regional"},{"t":"fact","big":"Kelantan has worst NRW at 62% losing nearly two-thirds of treated water","sub":"State water operator RM1.8 billion in debt cannot fund replacement","lens":"Security"},{"t":"fact","big":"Japan reduced NRW to 8% through systematic pipe replacement over 30 years","sub":"Malaysia would need RM45 billion investment to achieve similar results","lens":"Legal"},{"t":"reframe","big":"Water losses test whether infrastructure maintenance receives the same attention as construction","sub":""},{"t":"view","big":"RM7.2 billion in water losses yearly. Pipe replacement pays for itself; the obstacle is institutional inertia.","sub":""}]}