{"id":"1925","published":true,"opinionShift":44,"status":null,"edition":1,"headline":"Telecom Tower Sharing Saves Industry RM2.4 Billion Annually","context":"Malaysia mandatory tower sharing policy saved telecom industry RM2.4 billion by preventing duplicate construction in 2025.","stageScores":{"pa":76,"ba":72,"fc":83,"af":60,"ct":63,"sr":78},"finalScore":68.5,"cards":[{"t":"hook","big":"Tower sharing saved telecom industry RM2.4 billion in duplication","sub":"DNB and edotco manage shared infrastructure for all major operators"},{"t":"fact","big":"edotco operates 42,000 shared towers serving 4 operators simultaneously","sub":"Sharing reduced need for 28,000 additional towers built independently","lens":"Governance"},{"t":"fact","big":"Rental rates of RM2,800 monthly per operator 35% below regional average","sub":"Cost savings expected to flow to consumers through lower pricing","lens":"Political"},{"t":"fact","big":"Rural tower deployment increased 22% under sharing versus projected 8%","sub":"Shared economics make previously unviable rural locations feasible","lens":"Rights"},{"t":"reframe","big":"Tower sharing tests whether infrastructure cooperation produces consumer benefit or just industry savings","sub":""},{"t":"view","big":"RM2.4 billion saved through telecom tower sharing. Infrastructure sharing reduces cost without reducing competition.","sub":""}]}